atari_py/ale_c_wrapper.cpp
atari_py/import_roms.py
atari_py/ale_c_wrapper.h
atari_py/package_data.txt
atari_py/ale_python_interface.py
atari_py/games.py
atari_py/__init__.py
atari_py/atari_ntsc_rgb_palette.h
atari_py/atari_roms/tetris.bin
atari_py/ale_interface/libale_c.so
atari_py/ale_interface/md5.txt
atari_py/ale_interface/CMakeLists.txt
atari_py/ale_interface/src/ale_interface.hpp
atari_py/ale_interface/src/ale_interface.cpp
atari_py/ale_interface/src/module.mk
atari_py/ale_interface/src/main.cpp
atari_py/ale_interface/src/os_dependent/module.mk
atari_py/ale_interface/src/os_dependent/SettingsUNIX.cxx
atari_py/ale_interface/src/os_dependent/OSystemUNIX.cxx
atari_py/ale_interface/src/os_dependent/OSystemWin32.cxx
atari_py/ale_interface/src/os_dependent/OSystemUNIX.hxx
atari_py/ale_interface/src/os_dependent/FSNodePOSIX.cxx
atari_py/ale_interface/src/os_dependent/SettingsWin32.cxx
atari_py/ale_interface/src/os_dependent/OSystemWin32.hxx
atari_py/ale_interface/src/os_dependent/SettingsWin32.hxx
atari_py/ale_interface/src/os_dependent/SettingsUNIX.hxx
atari_py/ale_interface/src/os_dependent/FSNodeWin32.cxx
atari_py/ale_interface/src/common/Array.hxx
atari_py/ale_interface/src/common/Constants.cpp
atari_py/ale_interface/src/common/display_screen.cpp
atari_py/ale_interface/src/common/SoundSDL.hxx
atari_py/ale_interface/src/common/SoundSDL.cxx
atari_py/ale_interface/src/common/VideoModeList.hxx
atari_py/ale_interface/src/common/module.mk
atari_py/ale_interface/src/common/SoundExporter.cpp
atari_py/ale_interface/src/common/Version.hxx
atari_py/ale_interface/src/common/ColourPalette.cpp
atari_py/ale_interface/src/common/ColourPalette.hpp
atari_py/ale_interface/src/common/SoundNull.hxx
atari_py/ale_interface/src/common/Log.hpp
atari_py/ale_interface/src/common/SoundExporter.hpp
atari_py/ale_interface/src/common/Log.cpp
atari_py/ale_interface/src/common/stella.png
atari_py/ale_interface/src/common/ScreenExporter.cpp
atari_py-0.2.9.dist-info/top_level.txt
atari_py-0.2.9.dist-info/RECORD
atari_py-0.2.9.dist-info/METADATA
atari_py-0.2.9.dist-info/WHEEL
