Metadata-Version: 1.0
Name: atari-py
Version: 0.2.9
Summary: Python bindings to Atari games
Home-page: https://github.com/openai/atari-py
Author: OpenAI
Author-email: info@openai.com
License: UNKNOWN
Platform: UNKNOWN
